coffee/__init__.py
coffee/torch.py
oucoffee/__init__.py
oucoffee/coffee.py
oucoffee/torch.py
oucoffee-0.1.0.dist-info/LICENSE
oucoffee-0.1.0.dist-info/METADATA
oucoffee-0.1.0.dist-info/WHEEL
oucoffee-0.1.0.dist-info/top_level.txt
oucoffee-0.1.0.dist-info/zip-safe
oucoffee-0.1.0.dist-info/RECORD
