Metadata-Version: 2.1
Name: oucoffee
Version: 0.1.0
Summary: Dive into Deep Learning
Home-page: https://github.com/YiguoWang/oucoffee
Author: Oucoffee Developers
Author-email: 282832606@qq.com
License: MIT-0
Platform: UNKNOWN
Requires-Python: >=3.6
License-File: LICENSE
Requires-Dist: jupyter
Requires-Dist: numpy
Requires-Dist: matplotlib
Requires-Dist: requests
Requires-Dist: pandas
